[
    {
        "key": "cholera",
        "name": "Cholera",
        "administerFullVaccineGroup": ""
    },
    {
        "key": "d-ta-p-tdap-td",
        "name": "DTaP/Tdap/Td",
        "administerFullVaccineGroup": "No"
    },
    {
        "key": "hep-a",
        "name": "HepA",
        "administerFullVaccineGroup": ""
    },
    {
        "key": "hep-b",
        "name": "HepB",
        "administerFullVaccineGroup": ""
    },
    {
        "key": "hib",
        "name": "Hib",
        "administerFullVaccineGroup": ""
    },
    {
        "key": "hpv",
        "name": "HPV",
        "administerFullVaccineGroup": ""
    },
    {
        "key": "influenza",
        "name": "Influenza",
        "administerFullVaccineGroup": ""
    },
    {
        "key": "japanese-encephalitis",
        "name": "Japanese Encephalitis",
        "administerFullVaccineGroup": ""
    },
    {
        "key": "meningococcal",
        "name": "Meningococcal",
        "administerFullVaccineGroup": ""
    },
    {
        "key": "meningococcal-b",
        "name": "Meningococcal B",
        "administerFullVaccineGroup": ""
    },
    {
        "key": "mmr",
        "name": "MMR",
        "administerFullVaccineGroup": "Yes"
    },
    {
        "key": "pneumococcal",
        "name": "Pneumococcal",
        "administerFullVaccineGroup": ""
    },
    {
        "key": "polio",
        "name": "Polio",
        "administerFullVaccineGroup": ""
    },
    {
        "key": "rabies",
        "name": "Rabies",
        "administerFullVaccineGroup": ""
    },
    {
        "key": "rotavirus",
        "name": "Rotavirus",
        "administerFullVaccineGroup": ""
    },
    {
        "key": "typhoid",
        "name": "Typhoid",
        "administerFullVaccineGroup": ""
    },
    {
        "key": "varicella",
        "name": "Varicella",
        "administerFullVaccineGroup": ""
    },
    {
        "key": "yellow-fever",
        "name": "Yellow Fever",
        "administerFullVaccineGroup": ""
    },
    {
        "key": "zoster",
        "name": "Zoster",
        "administerFullVaccineGroup": ""
    }
]