{"cdcTestId":"2013-0302","testcaseName":"Dose 2 to 3, interval 4 weeks -4 days","vaccineGroup":"HIB","evaluationTestType":"Interval: At Absolute Minimum","forecastTestType":"Recommended based on age","assessmentDate":"2020-08-13T00:00:00","patient":{"dob":"2020-03-20T00:00:00","gender":"F"},"evaluation":{"seriesStatus":"Not complete","administeredDoses":[{"dateAdministered":"2020-05-20T00:00:00","vaccineName":"ACTHIB","cvx":"48","mvx":"PMC","evaluationStatus":"Valid","evaluationReason":null},{"dateAdministered":"2020-07-20T00:00:00","vaccineName":"ACTHIB","cvx":"48","mvx":"PMC","evaluationStatus":"Valid","evaluationReason":null},{"dateAdministered":"2020-08-13T00:00:00","vaccineName":"ACTHIB","cvx":"48","mvx":"PMC","evaluationStatus":"Valid","evaluationReason":null}]},"forecast":{"forecastNum":"4","earliestDate":"2021-03-20T00:00:00","recommendedDate":"2021-03-20T00:00:00","pastDueDate":"2021-08-16T00:00:00"},"doses":[{"dateAdministered":"2020-05-20T00:00:00","vaccineName":"ACTHIB","cvx":"48","mvx":"PMC","evaluationStatus":"Valid","evaluationReason":null},{"dateAdministered":"2020-07-20T00:00:00","vaccineName":"ACTHIB","cvx":"48","mvx":"PMC","evaluationStatus":"Valid","evaluationReason":null},{"dateAdministered":"2020-08-13T00:00:00","vaccineName":"ACTHIB","cvx":"48","mvx":"PMC","evaluationStatus":"Valid","evaluationReason":null}],"dateAdded":"2013-01-01T00:00:00","dateUpdated":"2020-05-27T08:35:25.48","generalDescription":"This test case describes when a child is administered the third dose of the Hib vaccine at an interval of 4 weeks - 4 days after the second dose  that the dose is valid.  Another dose should be forecast.","changedInVersion":"1.0","reasonForChange":""}