{"cdcTestId":"2013-0798","testcaseName":"#1 at 1 year","vaccineGroup":"VAR","evaluationTestType":"Age: At Minimum","forecastTestType":"Recommended based on age","assessmentDate":"2020-08-13T00:00:00","patient":{"dob":"2019-08-13T00:00:00","gender":"F"},"evaluation":{"seriesStatus":"Not complete","administeredDoses":[{"dateAdministered":"2020-08-13T00:00:00","vaccineName":"VARIVAX","cvx":"21","mvx":"MSD","evaluationStatus":"Valid","evaluationReason":null}]},"forecast":{"forecastNum":"2","earliestDate":"2020-11-13T00:00:00","recommendedDate":"2023-08-13T00:00:00","pastDueDate":"2026-09-09T00:00:00"},"doses":[{"dateAdministered":"2020-08-13T00:00:00","vaccineName":"VARIVAX","cvx":"21","mvx":"MSD","evaluationStatus":"Valid","evaluationReason":null}],"dateAdded":"2013-01-01T00:00:00","dateUpdated":"2018-01-02T14:24:41.674","generalDescription":"This test case describes the administering of dose #1 of varicella at 12 months or 1 year of age.","changedInVersion":"1.0","reasonForChange":""}