{"cdcTestId":"2016-0021","testcaseName":"Adolescent child 15 years -1 days with no previous history of HPV vaccine","vaccineGroup":"HPV","evaluationTestType":"No Doses Administered","forecastTestType":"Recommended based on interval","assessmentDate":"2020-08-13T00:00:00","patient":{"dob":"2005-08-14T00:00:00","gender":"M"},"evaluation":{"seriesStatus":"Not complete","administeredDoses":[]},"forecast":{"forecastNum":"1","earliestDate":"2014-08-14T00:00:00","recommendedDate":"2016-08-14T00:00:00","pastDueDate":"2018-09-10T00:00:00"},"doses":[],"dateAdded":"2016-12-02T00:00:00","dateUpdated":"2020-06-15T09:11:20.033","generalDescription":"This test case describes when an adolescent child age 15 years - 1 day has no previous history of the HPV vaccine that the first dose should be forecast.","changedInVersion":"1.0","reasonForChange":"v1.0 Corrected forecast dates to match test case title"}