{"evaluation":{"seriesStatus":"Not complete","administeredDoses":[{"dateAdministered":"2022-09-26T00:00:00","vaccineName":"varicella","cvx":"21","mvx":"","evaluationStatus":"Valid","evaluationReason":null},{"dateAdministered":"2022-10-19T00:00:00","vaccineName":"varicella","cvx":"21","mvx":"","evaluationStatus":"Not Valid","evaluationReason":"Interval: too short"}]},"forecast":{"forecastNum":"2","earliestDate":"2022-11-16T00:00:00","recommendedDate":"2022-11-16T00:00:00","pastDueDate":"2022-12-13T00:00:00"}}