{"evaluation":{"seriesStatus":"Not complete","administeredDoses":[{"dateAdministered":"2021-12-15T00:00:00","vaccineName":"ATTENUVAX","cvx":"05","mvx":"MSD","evaluationStatus":"Valid","evaluationReason":null},{"dateAdministered":"2022-06-01T00:00:00","vaccineName":"MERUVAX II","cvx":"06","mvx":"MSD","evaluationStatus":"Valid","evaluationReason":null},{"dateAdministered":"2022-10-19T00:00:00","vaccineName":"ATTENUVAX","cvx":"05","mvx":"MSD","evaluationStatus":"Valid","evaluationReason":null}]},"forecast":{"forecastNum":"1","earliestDate":"2022-11-16T00:00:00","recommendedDate":"2022-11-16T00:00:00","pastDueDate":"2022-11-16T00:00:00"}}