{
    "key": "2013-0789",
    "name": "#1 at 15 months",
    "cdcTestId": "2013-0789",
    "changedInVersion": "1.1",
    "dateAdded": "2013-01-01T00:00:00",
    "dateUpdated": "2018-01-02T14:19:57.503",
    "evaluation": {
        "administeredDoses": [
            {
                "cvx": "21",
                "dateAdministered": "2020-08-13T00:00:00",
                "evaluationReason": "",
                "evaluationStatus": "Valid",
                "mvx": "MSD",
                "vaccineName": "VARIVAX"
            }
        ],
        "seriesStatus": "Not complete"
    },
    "evaluationTestType": "All Valid: Forecast Test",
    "forecast": {
        "earliestDate": "2020-11-05T00:00:00",
        "forecastNum": "2",
        "pastDueDate": "2026-06-09T00:00:00",
        "recommendedDate": "2023-05-13T00:00:00"
    },
    "forecastTestType": "Recommended based on age",
    "generalDescription": "This test case describes the administering of dose #1 of varicella at 15 months. ",
    "patient": {
        "dob": "2019-05-13T00:00:00",
        "gender": "F",
        "medHistoryCode": "",
        "medHistoryCodeSys": "",
        "medHistoryText": "",
        "doses": [
            {
                "cvx": "21",
                "dateAdministered": "2020-08-13T00:00:00",
                "evaluationReason": "",
                "evaluationStatus": "Valid",
                "mvx": "MSD",
                "vaccineName": "VARIVAX"
            }
        ]
    },
    "reasonForChange": "Improved test case name and forecast test type to acurately reflect what was being tested",
    "testcaseName": "#1 at 15 months",
    "vaccineGroup": "VAR"
}