{"cdcTestId":"2013-0600","testcaseName":"Dose # 4 PCV 13 at 1 year.  Series complete. ","vaccineGroup":"PCV","evaluationTestType":"Age: At Minimum","forecastTestType":"Not recommended: series complete","assessmentDate":"2022-10-19T00:00:00","patient":{"dob":"2021-10-19T00:00:00","gender":"F"},"evaluation":{"seriesStatus":"Complete","administeredDoses":[{"dateAdministered":"2021-12-19T00:00:00","vaccineName":"PREVNAR 13","cvx":"133","mvx":"PFR","evaluationStatus":"Valid","evaluationReason":null},{"dateAdministered":"2022-02-19T00:00:00","vaccineName":"PREVNAR 13","cvx":"133","mvx":"PFR","evaluationStatus":"Valid","evaluationReason":null},{"dateAdministered":"2022-04-19T00:00:00","vaccineName":"PREVNAR 13","cvx":"133","mvx":"PFR","evaluationStatus":"Valid","evaluationReason":null},{"dateAdministered":"2022-10-19T00:00:00","vaccineName":"PREVNAR 13","cvx":"133","mvx":"PFR","evaluationStatus":"Valid","evaluationReason":null}]},"forecast":{"forecastNum":"-","earliestDate":"0001-01-01T00:00:00","recommendedDate":"0001-01-01T00:00:00","pastDueDate":"0001-01-01T00:00:00"},"doses":[{"dateAdministered":"2021-12-19T00:00:00","vaccineName":"PREVNAR 13","cvx":"133","mvx":"PFR","evaluationStatus":"Valid","evaluationReason":null},{"dateAdministered":"2022-02-19T00:00:00","vaccineName":"PREVNAR 13","cvx":"133","mvx":"PFR","evaluationStatus":"Valid","evaluationReason":null},{"dateAdministered":"2022-04-19T00:00:00","vaccineName":"PREVNAR 13","cvx":"133","mvx":"PFR","evaluationStatus":"Valid","evaluationReason":null},{"dateAdministered":"2022-10-19T00:00:00","vaccineName":"PREVNAR 13","cvx":"133","mvx":"PFR","evaluationStatus":"Valid","evaluationReason":null}],"dateAdded":"2013-01-01T00:00:00","dateUpdated":"2018-01-04T10:00:06.605","generalDescription":"This test case describes when dose #4 of the PCV13 vaccine is administered at age 12 months that the dose is considered to be valid.  The series is complete.","changedInVersion":"1.0","reasonForChange":""}