{"cdcTestId":"2013-0833","testcaseName":"LAIV given at age 3 years; VZ at age 3 years \u002B 28 days","vaccineGroup":"VAR","evaluationTestType":"Live Virus: At Minimum","forecastTestType":"Recommended based on age","assessmentDate":"2022-10-19T00:00:00","patient":{"dob":"2019-09-21T00:00:00","gender":"F"},"evaluation":{"seriesStatus":"Not complete","administeredDoses":[{"dateAdministered":"2022-09-21T00:00:00","vaccineName":"Flumist quadrivalent","cvx":"149","mvx":"MED","evaluationStatus":"Valid","evaluationReason":null},{"dateAdministered":"2022-10-19T00:00:00","vaccineName":"VARIVAX","cvx":"21","mvx":"MSD","evaluationStatus":"Valid","evaluationReason":null}]},"forecast":{"forecastNum":"2","earliestDate":"2023-01-11T00:00:00","recommendedDate":"2023-09-21T00:00:00","pastDueDate":"2026-10-18T00:00:00"},"doses":[{"dateAdministered":"2022-09-21T00:00:00","vaccineName":"Flumist quadrivalent","cvx":"149","mvx":"MED","evaluationStatus":"Valid","evaluationReason":null},{"dateAdministered":"2022-10-19T00:00:00","vaccineName":"VARIVAX","cvx":"21","mvx":"MSD","evaluationStatus":"Valid","evaluationReason":null}],"dateAdded":"2013-01-01T00:00:00","dateUpdated":"2018-03-12T16:57:27.278","generalDescription":"This test case describes when a Varicella vaccine is administered at least 28 days after an Influenza (LAIV) vaccine that the Varicella vaccine dose is considered to be valid. Forecast 2nd dose.","changedInVersion":"1.0","reasonForChange":""}