{
    "key": "2013-0451",
    "assessmentDate": "2020-08-13T00:00:00",
    "patient": {
        "dob": "2011-08-18T00:00:00",
        "gender": "F",
        "medHistoryCode": "",
        "medHistoryCodeSys": "",
        "medHistoryText": "",
        "doses": [
            {
                "cvx": "165",
                "dateAdministered": "2019-08-13T00:00:00",
                "evaluationReason": "Age: Too Young",
                "evaluationStatus": "Not Valid",
                "mvx": "",
                "vaccineName": "HPV9"
            },
            {
                "cvx": "165",
                "dateAdministered": "2020-08-13T00:00:00",
                "evaluationReason": "Age: Too Young",
                "evaluationStatus": "Not Valid",
                "mvx": "",
                "vaccineName": "HPV9"
            }
        ]
    }
}