{
    "key": "2013-0447",
    "name": "#3 with interval of 4 mo from #2",
    "cdcTestId": "2013-0447",
    "changedInVersion": "1.0",
    "dateAdded": "2013-01-01T00:00:00",
    "dateUpdated": "2020-06-15T08:46:54.307",
    "evaluation": {
        "administeredDoses": [
            {
                "cvx": "165",
                "dateAdministered": "2020-02-13T00:00:00",
                "evaluationReason": "",
                "evaluationStatus": "Valid",
                "mvx": "",
                "vaccineName": "HPV9"
            },
            {
                "cvx": "165",
                "dateAdministered": "2020-04-13T00:00:00",
                "evaluationReason": "",
                "evaluationStatus": "Valid",
                "mvx": "",
                "vaccineName": "HPV9"
            },
            {
                "cvx": "165",
                "dateAdministered": "2020-08-13T00:00:00",
                "evaluationReason": "",
                "evaluationStatus": "Valid",
                "mvx": "",
                "vaccineName": "HPV9"
            }
        ],
        "seriesStatus": "Complete"
    },
    "evaluationTestType": "Interval: At Recommended",
    "forecast": {
        "earliestDate": "0001-01-01T00:00:00",
        "forecastNum": "-",
        "pastDueDate": "0001-01-01T00:00:00",
        "recommendedDate": "0001-01-01T00:00:00"
    },
    "forecastTestType": "Not recommended: series complete",
    "generalDescription": "This test case describes when a child is administered the third dose of the HPV vaccine four months after the second dose that the dose is valid.  The series is complete.",
    "patient": {
        "dob": "2009-02-13T00:00:00",
        "gender": "F",
        "medHistoryCode": "",
        "medHistoryCodeSys": "",
        "medHistoryText": "",
        "doses": [
            {
                "cvx": "165",
                "dateAdministered": "2020-02-13T00:00:00",
                "evaluationReason": "",
                "evaluationStatus": "Valid",
                "mvx": "",
                "vaccineName": "HPV9"
            },
            {
                "cvx": "165",
                "dateAdministered": "2020-04-13T00:00:00",
                "evaluationReason": "",
                "evaluationStatus": "Valid",
                "mvx": "",
                "vaccineName": "HPV9"
            },
            {
                "cvx": "165",
                "dateAdministered": "2020-08-13T00:00:00",
                "evaluationReason": "",
                "evaluationStatus": "Valid",
                "mvx": "",
                "vaccineName": "HPV9"
            }
        ]
    },
    "reasonForChange": "",
    "testcaseName": "#3 with interval of 4 mo from #2",
    "vaccineGroup": "HPV"
}