{"assessmentDate":"2022-10-19T00:00:00","patient":{"dob":"1971-09-21T00:00:00","gender":"F"},"doses":[{"dateAdministered":"2022-09-21T00:00:00","vaccineName":"Pfizer-BioNTech COVID-19 Vaccine (EUA labeled)  COMIRNATY (BLA labeled)","cvx":"300","mvx":"PFR","evaluationStatus":"Valid","evaluationReason":null},{"dateAdministered":"2022-10-19T00:00:00","vaccineName":"Pfizer-BioNTech COVID-19 Vaccine (EUA labeled)  COMIRNATY (BLA labeled)","cvx":"300","mvx":"PFR","evaluationStatus":"Valid","evaluationReason":null}]}