{"cdcTestId":"2013-0049","testcaseName":"Dose 3 to dose 4 interval 6 months-4 days","vaccineGroup":"DTAP","evaluationTestType":"All Valid: Forecast Test","forecastTestType":"Recommended based on age","assessmentDate":"2022-10-19T00:00:00","patient":{"dob":"2021-10-13T00:00:00","gender":"F"},"evaluation":{"seriesStatus":"Not complete","administeredDoses":[{"dateAdministered":"2021-12-14T00:00:00","vaccineName":"DTaP, unspecified formulation","cvx":"107","mvx":"","evaluationStatus":"Valid","evaluationReason":null},{"dateAdministered":"2022-02-14T00:00:00","vaccineName":"DTaP, unspecified formulation","cvx":"107","mvx":"","evaluationStatus":"Valid","evaluationReason":null},{"dateAdministered":"2022-04-19T00:00:00","vaccineName":"DTaP, unspecified formulation","cvx":"107","mvx":"","evaluationStatus":"Valid","evaluationReason":null},{"dateAdministered":"2022-10-15T00:00:00","vaccineName":"DTaP, unspecified formulation","cvx":"107","mvx":"","evaluationStatus":"Valid","evaluationReason":null}]},"forecast":{"forecastNum":"5","earliestDate":"2025-10-13T00:00:00","recommendedDate":"2025-10-13T00:00:00","pastDueDate":"2028-10-12T00:00:00"},"doses":[{"dateAdministered":"2021-12-14T00:00:00","vaccineName":"DTaP, unspecified formulation","cvx":"107","mvx":"","evaluationStatus":"Valid","evaluationReason":null},{"dateAdministered":"2022-02-14T00:00:00","vaccineName":"DTaP, unspecified formulation","cvx":"107","mvx":"","evaluationStatus":"Valid","evaluationReason":null},{"dateAdministered":"2022-04-19T00:00:00","vaccineName":"DTaP, unspecified formulation","cvx":"107","mvx":"","evaluationStatus":"Valid","evaluationReason":null},{"dateAdministered":"2022-10-15T00:00:00","vaccineName":"DTaP, unspecified formulation","cvx":"107","mvx":"","evaluationStatus":"Valid","evaluationReason":null}],"dateAdded":"2013-01-01T00:00:00","dateUpdated":"2022-08-25T09:34:40.866","generalDescription":"This test case describes when a child is administered dose four of the DTaP vaccine at an interval of 6 months - 4 days months after the third dose that the dose is valid.  Another dose should be forecast.","changedInVersion":"1.0","reasonForChange":""}