{"cdcTestId":"2022-0079","testcaseName":"Patient is 16 years of age and has been administered dose #1 as Pfizer and dose #2 as Moderna and dose #3 bivalent dose","vaccineGroup":"COVID-19","evaluationTestType":"All Valid: Forecast Test","forecastTestType":"Recommended based on interval","assessmentDate":"2022-10-19T00:00:00","patient":{"dob":"2006-07-19T00:00:00","gender":"F"},"evaluation":{"seriesStatus":"Complete","administeredDoses":[{"dateAdministered":"2022-07-19T00:00:00","vaccineName":"Pfizer-BioNTech COVID-19 Vaccine (EUA labeled)  COMIRNATY (BLA labeled)","cvx":"208","mvx":"PFR","evaluationStatus":"Valid","evaluationReason":null},{"dateAdministered":"2022-08-16T00:00:00","vaccineName":"Moderna COVID-19 Vaccine (non-US Spikevax)","cvx":"207","mvx":"MOD","evaluationStatus":"Valid","evaluationReason":null},{"dateAdministered":"2022-10-11T00:00:00","vaccineName":"Moderna COVID-19 Vaccine (non-US Spikevax)","cvx":"229","mvx":"MOD","evaluationStatus":"Valid","evaluationReason":null}]},"forecast":{"forecastNum":"","earliestDate":"0001-01-01T00:00:00","recommendedDate":"0001-01-01T00:00:00","pastDueDate":"0001-01-01T00:00:00"},"doses":[{"dateAdministered":"2022-07-19T00:00:00","vaccineName":"Pfizer-BioNTech COVID-19 Vaccine (EUA labeled)  COMIRNATY (BLA labeled)","cvx":"208","mvx":"PFR","evaluationStatus":"Valid","evaluationReason":null},{"dateAdministered":"2022-08-16T00:00:00","vaccineName":"Moderna COVID-19 Vaccine (non-US Spikevax)","cvx":"207","mvx":"MOD","evaluationStatus":"Valid","evaluationReason":null},{"dateAdministered":"2022-10-11T00:00:00","vaccineName":"Moderna COVID-19 Vaccine (non-US Spikevax)","cvx":"229","mvx":"MOD","evaluationStatus":"Valid","evaluationReason":null}],"dateAdded":"2020-10-06T20:00:00","dateUpdated":"2022-09-27T12:12:27.762","generalDescription":"This test case describes when a patient that is 16 years is administered the first dose of the Covid-19 vaccine as Pfizer, the second dose as the Moderna Covid-19 vaccine, and the third doses as Bivalent Moderna Covid-19 vaccine that the doses are valid. Series is complete.","changedInVersion":"4.27","reasonForChange":""}